codecrumbs/__init__.py
codecrumbs/__main__.py
codecrumbs/_argument.py
codecrumbs/_attribute.py
codecrumbs/_calling_expression.py
codecrumbs/_rewrite_code.py
codecrumbs/pytest_plugin.py
codecrumbs-0.1.0.dist-info/WHEEL
codecrumbs-0.1.0.dist-info/METADATA
codecrumbs-0.1.0.dist-info/LICENSE
codecrumbs-0.1.0.dist-info/entry_points.txt
codecrumbs-0.1.0.dist-info/RECORD
