Metadata-Version: 2.1
Name: codecrumbs
Version: 0.1.0
Summary: leave codecrumbs behind so that other can adopt the changes
Home-page: https://github.com/15r10nk/codecrumbs
License: MIT
Author: Frank Hoffmann
Author-email: 15r10nk@polarbit.de
Requires-Python: >=3.8,<4.0
Classifier: Development Status :: 4 - Beta
Classifier: Framework :: Pytest
Classifier: Intended Audience :: Developers
Classifier: License :: OSI Approved :: MIT License
Classifier: Operating System :: OS Independent
Classifier: Programming Language :: Python :: 3
Classifier: Programming Language :: Python :: 3.8
Classifier: Programming Language :: Python :: 3.9
Classifier: Programming Language :: Python :: 3.10
Classifier: Programming Language :: Python :: 3.11
Classifier: Programming Language :: Python :: Implementation :: CPython
Requires-Dist: asttokens (>=2.2.1,<3.0.0) ; python_version >= "3.11"
Requires-Dist: executing (>=1.2.0,<2.0.0) ; python_version >= "3.11"
Project-URL: Repository, https://github.com/15r10nk/codecrumbs
